{
  "name": "双膝关节疼痛伴晨僵",
  "difficulty": 2,
  "time_limit": 20,
  "description": "中年女性，因双膝关节疼痛伴晨僵3个月就诊。请通过系统的护理病史采集，了解疼痛特点、功能影响、既往诊疗经过和相关危险因素。",
  "patient_info": {
    "name": "张美华",
    "age": 55,
    "gender": "女"
  },
  "chief_complaint": "双膝关节疼痛伴晨僵3个月",
  "opening_line": "护士你好，我这膝盖疼了快三个月了，早上起来硬邦邦的动不了，得活动好一会儿才能缓过来，最近上下楼都费劲，想来看看是怎么回事。",
  "present_illness": "患者3个月前无明显诱因出现双膝关节疼痛，以右膝为重。疼痛性质为酸痛、胀痛，久坐后和早晨起床时明显，活动30-40分钟后逐渐减轻。晨僵持续约45-60分钟。近1个月加重，上楼梯和下蹲困难，走路超过15分钟即感疼痛加剧。无关节红肿发热，无外伤史，无发热。自行使用热敷和外用膏药（云南白药贴膏），效果不明显，疼痛仍反复。近期因疼痛影响睡眠，入睡困难。食欲可，二便正常。",
  "past_history": "有高血压病史5年，规律服药控制可。否认糖尿病、冠心病史。否认肝炎、结核等传染病史。无手术史。近半年自觉体力不如前，体重无明显变化。",
  "medication_history": "口服硝苯地平控释片30mg qd控制血压，近3个月为缓解关节痛自行加用布洛芬缓释胶囊300mg bid（间断使用），近2周改为每日使用。外用云南白药贴膏。否认激素类药物使用。",
  "allergy_history": "否认药物、食物及其他过敏史。",
  "family_history": "母亲有类风湿关节炎病史20余年，长期服药。父亲有高血压史，体健。兄弟姐妹中有一姐自诉\"关节不好\"，具体不详。",
  "social_history": "退休小学教师，与丈夫同住，子女在外地工作。平日喜欢跳广场舞和散步，近3个月因疼痛活动量明显减少，体重增加约2kg。饮食偏咸偏油。否认吸烟饮酒。生活自理，但做家务（拖地、提重物）时膝关节疼痛加重。近半年情绪略低落，因担心以后\"腿不好了\"影响生活。",
  "communication_style": "患者性格温和，配合医护，能清晰描述症状。但因为疼痛持续时间长、自行处理效果不佳，有些焦虑，多次表达'会不会以后都这样了'的担忧。偶尔会跳题描述其他不适（如'有时候手指也会有点僵'），但主诉集中在膝关节。文化程度大专，普通话标准。护理学生需要评估其对慢性疼痛的认知、自我管理能力和心理状态。",
  "hidden_info": [
    "患者近2周因疼痛加重，布洛芬使用频次从'间断'增加到'每天吃'，且未告知医生",
    "患者母亲有明确类风湿关节炎病史，但患者未主动提及，需追问家族史才透露",
    "患者近半年情绪低落、睡眠差，可能与慢性疼痛和功能受限有关的焦虑情绪",
    "患者近3个月完全停止了广场舞和散步活动，体重增加2kg，可能加重关节负担"
  ],
  "hidden_info_rules": [
    {
      "topic": "止痛药滥用",
      "content": "近2周因疼痛加重，布洛芬从间断服用增加到每天吃，未告知医生",
      "trigger_keywords": ["止痛药", "布洛芬", "吃几次", "每天", "频次", "剂量", "用药", "怎么吃"]
    },
    {
      "topic": "母亲类风湿",
      "content": "母亲有明确类风湿关节炎病史",
      "trigger_keywords": ["家族", "家人", "父母", "母亲", "遗传", "风湿", "类风湿", "家里有"]
    },
    {
      "topic": "焦虑情绪",
      "content": "近半年情绪低落、睡眠差，可能与慢性疼痛和功能受限有关",
      "trigger_keywords": ["情绪", "睡眠", "心情", "焦虑", "抑郁", "睡不好", "心态", "压力"]
    },
    {
      "topic": "活动减少",
      "content": "近3个月完全停止了广场舞和散步，体重增加2kg，可能加重关节负担",
      "trigger_keywords": ["运动", "活动", "锻炼", "广场舞", "散步", "体重", "重了", "胖", "生活方式"]
    }
  ],
  "required_inquiries": [
    "疼痛起病时间、诱因和演变过程",
    "疼痛部位、性质和程度评估",
    "晨僵持续时间（>30分钟提示炎症性）",
    "加重和缓解因素（活动后减轻 vs 加重）",
    "疼痛对日常功能的影响（上下楼、行走、家务）",
    "既往诊疗经过和自我处理措施",
    "NSAIDs使用情况（频次、剂量、时长）",
    "高血压病史和降压药物",
    "关节外症状（如手指僵硬、乏力等）",
    "类风湿关节炎家族史",
    "既往活动水平和近期的变化",
    "体重变化情况",
    "睡眠质量和情绪状态",
    "社会支持和生活自理能力"
  ],
  "scoring_criteria": {
    "沟通技能": {
      "max": 42,
      "description": "评估学生在与病人互动时的沟通技巧和人际交往能力",
      "items": [
        "学生与病人打招呼并问候",
        "学生询问病人的姓名和个人信息",
        "学生自我介绍并说明角色",
        "学生展示尊重和关注",
        "学生识别病人的主要问题",
        "学生鼓励病人讲述症状（当前病史）",
        "学生使用开放性问题开始，并逐步转向封闭性问题",
        "学生专心聆听病人，避免打断",
        "学生通过语言技巧帮助病人表达",
        "学生通过非语言技巧（如肢体语言）促进沟通",
        "学生获取病史的时间顺序和症状详细情况",
        "学生询问病人的生活习惯和过敏史",
        "学生接受病人的感受和观点，而不做评判",
        "学生在访谈过程中保持合理的时间管理"
      ]
    },
    "病史采集": {
      "max": 15,
      "description": "评估学生在采集病史时的能力，确保能够全面地收集病人的病史信息",
      "items": [
        "学生清晰地询问病人的过往病史，包括疫苗接种史、儿童和成人时期的疾病史",
        "学生询问病人的住院和手术史",
        "学生记录病人描述的症状，确保完整和准确",
        "学生询问病人的家族病史及遗传背景",
        "学生总结病史并确保病人没有遗漏重要信息"
      ]
    }
  }
}
